leabra/__init__.py
leabra/connection.py
leabra/layer.py
leabra/network.py
leabra/unit.py
leabra_psyneulink-0.3.2.dist-info/METADATA
leabra_psyneulink-0.3.2.dist-info/WHEEL
leabra_psyneulink-0.3.2.dist-info/top_level.txt
leabra_psyneulink-0.3.2.dist-info/RECORD
